{
  "id": "ms-ro-a-avea-427218f0",
  "lang": "ro",
  "part_of_speech": "verb",
  "tags": [
    "level:a1",
    "etymology:latin",
    "topic:concepts-abstract",
    "register:neutral",
    "property:state"
  ],
  "metadata": {
    "author": "mschwehl",
    "source": "swipedict-ms-ro",
    "contentVersion": 1,
    "schemaVersion": "1.0"
  },
  "data": {
    "headword": "a avea",
    "definition": "a fi în posesia a ceva",
    "pronunciation": "/a aˈve.a/",
    "etymology": {
      "text": "Verbul românesc „a avea“ provine din latină „habere“, care înseamnă „a avea, a poseda“.",
      "source": "Etymological Dictionaries, Linguistic Analysis"
    }
  },
  "examples": [
    {
      "text": "Eu am o carte."
    },
    {
      "text": "Ai un câine?"
    },
    {
      "text": "El are mulți prieteni."
    },
    {
      "text": "Noi avem timp."
    },
    {
      "text": "Aveți un obiectiv?"
    },
    {
      "text": "Ei au o casă frumoasă."
    },
    {
      "text": "Am mâncat un măr."
    },
    {
      "text": "Voi avea un câine."
    },
    {
      "text": "Aibă răbdare!"
    }
  ],
  "relatedWords": [
    {
      "text": "posesie"
    },
    {
      "text": "caracteristică"
    },
    {
      "text": "familie"
    },
    {
      "text": "prieten"
    }
  ]
}