{
  "id": "ms-ro-a-culege-21047d5c",
  "lang": "ro",
  "part_of_speech": "verb",
  "tags": [
    "level:b1",
    "etymology:latin",
    "topic:nature-environment",
    "register:neutral",
    "property:action"
  ],
  "metadata": {
    "author": "mschwehl",
    "source": "swipedict-ms-ro",
    "contentVersion": 1,
    "schemaVersion": "1.0"
  },
  "data": {
    "headword": "a culege",
    "definition": "a culege fructele sau plantele coapte",
    "pronunciation": "/a kuˈled͡ʒe/",
    "etymology": {
      "text": "Verbul românesc „a culege“ provine din latină, de la „colligere“, care înseamnă „a aduna, a strânge“.",
      "source": "Etymological Dictionaries, Linguistic Analysis"
    }
  },
  "examples": [
    {
      "text": "Eu culeg merele din grădină."
    },
    {
      "text": "Culegi legumele?"
    },
    {
      "text": "Ea culege florile primăvara."
    },
    {
      "text": "Noi culesc în acest an multe fructe."
    },
    {
      "text": "Culegeți vișinele?"
    },
    {
      "text": "Ei culeg plantele agricole."
    },
    {
      "text": "Am încheiat cu succes culesul grâului."
    },
    {
      "text": "Ei au cules căpșunile."
    },
    {
      "text": "El culegea o cantitate mare de legume în fiecare vară."
    },
    {
      "text": "Culesesem deja strugurii când a început să plouă."
    },
    {
      "text": "Voi culege fructele săptămâna viitoare."
    },
    {
      "text": "Ea o să culeagă plantele agricole mâine."
    },
    {
      "text": "Aș culege nucile toamna, dacă aș avea timp."
    },
    {
      "text": "Ar fi bine să finalizezi culesul astăzi."
    },
    {
      "text": "Culege fructele la timp!"
    },
    {
      "text": "Culegeți cartofii, vă rog!"
    },
    {
      "text": "Merele culese sunt proaspete."
    },
    {
      "text": "Culegând strugurii, învăț multe despre perioada de recoltare."
    }
  ],
  "relatedWords": [
    {
      "text": "ferma"
    },
    {
      "text": "timpul recoltei"
    },
    {
      "text": "fruct"
    },
    {
      "text": "cereale"
    }
  ]
}