{
  "id": "ms-ro-a-se-cuibari-73df6d96",
  "lang": "ro",
  "part_of_speech": "verb",
  "tags": [
    "level:b1",
    "etymology:latin",
    "topic:emotions-character",
    "register:neutral",
    "property:action"
  ],
  "metadata": {
    "author": "mschwehl",
    "source": "swipedict-ms-ro",
    "contentVersion": 1,
    "schemaVersion": "1.0"
  },
  "data": {
    "headword": "a se cuibări",
    "definition": "A se lipi sau a se strânge aproape de cineva pentru a căuta căldură, confort sau afecțiune.",
    "pronunciation": "/a se kwiˈbəri/",
    "etymology": {
      "text": "Verbul românesc „a se cuibări” derivă din substantivul latin 'cupa' (butoi, recipient), folosit metaforic pentru cuib sau loc protejat, evoluând într-un verb care descrie acțiunea de a se așeza într-un loc protejat.",
      "source": "Dicționare etimologice, studii lingvistice"
    }
  },
  "examples": [
    {
      "text": "Copilul se cuibărește de mama lui."
    },
    {
      "text": "Ne cuibărim împreună pe canapea."
    },
    {
      "text": "După plimbare, s-au cuibărit sub pătură."
    },
    {
      "text": "Pisica îi place să se cuibărească la soare."
    }
  ],
  "relatedWords": [
    {
      "text": "a se sprijini"
    },
    {
      "text": "siguranță"
    },
    {
      "text": "a se alinta"
    },
    {
      "text": "a îmbrățișa"
    }
  ]
}