{
  "id": "ms-ro-a-spala-rufe-fee0dd42",
  "lang": "ro",
  "part_of_speech": "phrase",
  "tags": [
    "level:a1",
    "etymology:latin",
    "topic:home-living",
    "register:neutral",
    "property:action"
  ],
  "metadata": {
    "author": "mschwehl",
    "source": "swipedict-ms-ro",
    "contentVersion": 1,
    "schemaVersion": "1.0"
  },
  "data": {
    "headword": "a spăla rufe",
    "definition": "A curăța haine sau textile folosind apă și detergent.",
    "pronunciation": "/a spəˈla ˈrufe/",
    "etymology": {
      "text": "Verbul românesc „a spăla” provine din latină, din 'spalare', care înseamnă 'a spăla', iar „rufe” derivă din latinescul 'roupa', însemnând haine.",
      "source": "Dicționare etimologice, studii lingvistice"
    }
  },
  "examples": [
    {
      "text": "Spăl rufele în fiecare sâmbătă."
    },
    {
      "text": "Poți, te rog, să speli rufele?"
    },
    {
      "text": "Rufele sunt curate și proaspăt spălate."
    },
    {
      "text": "Trebuie să spălăm rufele înainte de a le usca."
    }
  ],
  "relatedWords": [
    {
      "text": "a călca"
    },
    {
      "text": "a usca"
    },
    {
      "text": "mașină de spălat"
    },
    {
      "text": "detergent"
    }
  ]
}