{
  "id": "ms-ro-caruta-db31fe0b",
  "lang": "ro",
  "part_of_speech": "noun",
  "tags": [
    "level:b1",
    "etymology:latin",
    "topic:transport-movement",
    "register:neutral",
    "property:concrete"
  ],
  "metadata": {
    "author": "mschwehl",
    "source": "swipedict-ms-ro",
    "contentVersion": 1,
    "schemaVersion": "1.0"
  },
  "data": {
    "headword": "căruță",
    "definition": "Un vehicul tras de cai, folosit pentru transportul persoanelor.",
    "pronunciation": "/kəˈru.t͡sə/",
    "etymology": {
      "text": "Cuvântul românesc „căruță” provine din latinescul 'carrus', care înseamnă 'căruță' sau 'car', preluat în limba română din latină.",
      "source": "Etymological Dictionaries, Linguistic Analysis"
    },
    "genus": "feminine"
  },
  "examples": [
    {
      "text": "Căruța era trasă de doi cai."
    },
    {
      "text": "În trecut, căruța era un mijloc important de transport."
    },
    {
      "text": "Am făcut o plimbare cu căruța prin parc."
    },
    {
      "text": "Căruța stă în fața castelului."
    }
  ],
  "relatedWords": [
    {
      "text": "cal"
    },
    {
      "text": "car"
    },
    {
      "text": "a merge cu căruța"
    },
    {
      "text": "vehicul tras de cai"
    }
  ]
}