{
  "id": "ms-ro-ecologic-ac4edaf1",
  "lang": "ro",
  "part_of_speech": "adjective",
  "tags": [
    "level:b2",
    "etymology:latin",
    "topic:nature-environment",
    "register:neutral",
    "property:quality"
  ],
  "metadata": {
    "author": "mschwehl",
    "source": "swipedict-ms-ro",
    "contentVersion": 1,
    "schemaVersion": "1.0"
  },
  "data": {
    "headword": "ecologic",
    "definition": "Care protejează mediul și nu îl dăunează.",
    "pronunciation": "/ekoˈloʒik/",
    "etymology": {
      "text": "Adjectivul românesc „ecologic” provine din grecescul 'oikos' (casă, mediu), prin latină și franceză.",
      "source": "Etymological Dictionaries, Linguistic Analysis"
    }
  },
  "examples": [
    {
      "text": "Această ambalare este ecologică."
    },
    {
      "text": "Folosim produse ecologice."
    },
    {
      "text": "Tehnologiile ecologice sunt importante."
    }
  ],
  "relatedWords": [
    {
      "text": "prietenos"
    },
    {
      "text": "durabilitate"
    },
    {
      "text": "protecție"
    },
    {
      "text": "mediu"
    }
  ]
}