{
  "id": "ms-ro-medicament-9a9c723a",
  "lang": "ro",
  "part_of_speech": "noun",
  "tags": [
    "level:b1",
    "etymology:latin",
    "topic:body-health",
    "register:neutral",
    "property:concrete"
  ],
  "metadata": {
    "author": "mschwehl",
    "source": "swipedict-ms-ro",
    "contentVersion": 1,
    "schemaVersion": "1.0"
  },
  "data": {
    "headword": "medicament",
    "definition": "Substanță sau preparat folosit pentru prevenirea, tratarea sau vindecarea bolilor.",
    "pronunciation": "/mediˈkament/",
    "etymology": {
      "text": "Cuvântul românesc „medicament” provine direct din latină, de la 'medicamentum', care înseamnă 'remediu', derivat din 'medicare' (a trata, a vindeca).",
      "source": "Etymological Dictionaries, Linguistic Analysis"
    },
    "genus": "neuter"
  },
  "examples": [
    {
      "text": "Medicamentul trebuie administrat de trei ori pe zi."
    },
    {
      "text": "Doctorul a prescris un medicament nou pentru dureri."
    },
    {
      "text": "Multe medicamente au efecte secundare."
    },
    {
      "text": "Vă rugăm să păstrați medicamentul departe de copii."
    }
  ],
  "relatedWords": [
    {
      "text": "medicament"
    },
    {
      "text": "tratament"
    },
    {
      "text": "remediu"
    },
    {
      "text": "comprimat"
    }
  ]
}