{
  "id": "ms-ro-motorina-3ca4766f",
  "lang": "ro",
  "part_of_speech": "noun",
  "tags": [
    "level:b2",
    "etymology:latin",
    "topic:concepts-abstract",
    "topic:work-education",
    "register:neutral",
    "property:concrete"
  ],
  "metadata": {
    "author": "mschwehl",
    "source": "swipedict-ms-ro",
    "contentVersion": 1,
    "schemaVersion": "1.0"
  },
  "data": {
    "headword": "motorină",
    "definition": "Un combustibil lichid utilizat în special pentru încălzire și motoare diesel; în contextul 'Heizöl' bezeichnet es Heizöl als Brennstoff.",
    "pronunciation": "/motorˈinə/",
    "etymology": {
      "text": "Cuvântul românesc „motorină” provine din franceza 'moteur' (motor), cu sufixul '-ină' care indică o substanță, desemnând un combustibil lichid folosit pentru motoare și încălzire.",
      "source": "Etymological Dictionaries, Linguistic Analysis"
    },
    "genus": "feminine"
  },
  "examples": [
    {
      "text": "Motorina pentru încălzire este folosită iarna pentru încălzire."
    },
    {
      "text": "Prețurile motorinei pentru încălzire au crescut în ultimele luni."
    },
    {
      "text": "Multe gospodării folosesc motorina pentru încălzire ca sursă de energie."
    },
    {
      "text": "Uleiul este o materie primă importantă pentru industrie."
    }
  ],
  "relatedWords": [
    {
      "text": "benzină"
    },
    {
      "text": "motorină pentru încălzire"
    },
    {
      "text": "combustibil"
    },
    {
      "text": "sondă de petrol"
    }
  ]
}