{
  "id": "ms-ro-sase-7c8ad9fc",
  "lang": "ro",
  "part_of_speech": "numeral",
  "tags": [
    "level:a1",
    "etymology:latin",
    "topic:time-numbers",
    "register:neutral",
    "property:concrete"
  ],
  "metadata": {
    "author": "mschwehl",
    "source": "swipedict-ms-ro",
    "contentVersion": 1,
    "schemaVersion": "1.0"
  },
  "data": {
    "headword": "șase",
    "definition": "Numărul 6, un număr natural între cinci și șapte.",
    "pronunciation": "/ˈʃase/",
    "etymology": {
      "text": "Cuvântul românesc „șase” provine direct din latină, din cuvântul 'sex', care desemna cifra șase, având originea în proto-indo-europeanul *seks-.",
      "source": "Etymological Dictionaries, Linguistic Analysis"
    }
  },
  "examples": [
    {
      "text": "Am cumpărat șase mere."
    },
    {
      "text": "Șase este un număr par."
    },
    {
      "text": "Trenul pleacă la ora șase."
    },
    {
      "text": "Ea are șase frați."
    }
  ],
  "relatedWords": [
    {
      "text": "cinci"
    },
    {
      "text": "număr"
    },
    {
      "text": "șapte"
    },
    {
      "text": "număr"
    }
  ]
}