{
  "id": "ms-ro-sonerie-4d269f5d",
  "lang": "ro",
  "part_of_speech": "noun",
  "tags": [
    "level:a2",
    "etymology:germanic",
    "topic:home-living",
    "register:neutral",
    "property:concrete"
  ],
  "metadata": {
    "author": "mschwehl",
    "source": "swipedict-ms-ro",
    "contentVersion": 1,
    "schemaVersion": "1.0"
  },
  "data": {
    "headword": "sonerie",
    "definition": "Un dispozitiv care emite un sunet atunci când este apăsat, folosit pentru a atrage atenția, de exemplu la o ușă.",
    "pronunciation": "/soˈne.ri.e/",
    "etymology": {
      "text": "Cuvântul românesc „sonerie” provine din francezul 'sonnerie', care la rândul său derivă din latină 'sonus', însemnând 'sunet, ton'.",
      "source": "Dicționare etimologice, Analize lingvistice"
    },
    "genus": "feminine"
  },
  "examples": [
    {
      "text": "Soneria de la ușa casei nu funcționează."
    },
    {
      "text": "Te rog să apeși soneria când ajungi."
    },
    {
      "text": "Soneria a sunat tare și clar."
    },
    {
      "text": "Am instalat o sonerie nouă."
    }
  ],
  "relatedWords": [
    {
      "text": "clopot"
    },
    {
      "text": "semnal"
    },
    {
      "text": "ton"
    },
    {
      "text": "ușă"
    }
  ]
}