{
  "id": "ms-ro-terasa-659ba4c6",
  "lang": "ro",
  "part_of_speech": "noun",
  "tags": [
    "level:b1",
    "etymology:french",
    "topic:home-living",
    "register:neutral",
    "property:concrete"
  ],
  "metadata": {
    "author": "mschwehl",
    "source": "swipedict-ms-ro",
    "contentVersion": 1,
    "schemaVersion": "1.0"
  },
  "data": {
    "headword": "terasă",
    "definition": "O zonă exterioară plană, de obicei pavata sau betonată, adiacentă unei clădiri, folosită pentru ședere sau relaxare.",
    "pronunciation": "/teˈrasə/",
    "etymology": {
      "text": "Cuvântul românesc „terasă“ provine din francezul „terrasse“, care la rândul său vine din italianul „terrazza“ și desemnează o suprafață plană, adesea în aer liber.",
      "source": "Etymological Dictionaries, Linguistic Analysis"
    },
    "genus": "feminine"
  },
  "examples": [
    {
      "text": "Stăm diseară pe terasă și ne bucurăm de apusul soarelui."
    },
    {
      "text": "Terasa este decorată cu flori și mobilier de grădină."
    },
    {
      "text": "În timpul verii mâncăm adesea pe terasă."
    },
    {
      "text": "Terasa se învecinează direct cu sufrageria."
    }
  ],
  "relatedWords": [
    {
      "text": "balcon"
    },
    {
      "text": "grădină"
    },
    {
      "text": "curte"
    },
    {
      "text": "verandă"
    }
  ]
}