{
  "id": "ms-ro-vot-1a300fbd",
  "lang": "ro",
  "part_of_speech": "noun",
  "tags": [
    "level:b1",
    "etymology:latin",
    "topic:people-society",
    "register:neutral",
    "property:concrete"
  ],
  "metadata": {
    "author": "mschwehl",
    "source": "swipedict-ms-ro",
    "contentVersion": 1,
    "schemaVersion": "1.0"
  },
  "data": {
    "headword": "vot",
    "definition": "Dreptul oder die Handlung, bei einer Wahl oder Abstimmung seine Meinung durch eine Wahlstimme auszudrücken.",
    "pronunciation": "/vot/",
    "etymology": {
      "text": "Cuvântul românesc „vot” provine direct din latinescul 'votum', care inițial însemna 'vot, jurământ, dorință' și ulterior a căpătat sensul de 'voce exprimată la o alegere'.",
      "source": "Etymological Dictionaries, Linguistic Analysis"
    },
    "genus": "neuter"
  },
  "examples": [
    {
      "text": "Fiecare cetățean are dreptul să-și dea votul."
    },
    {
      "text": "Participarea la vot a fost foarte mare, mulți oameni și-au exprimat votul."
    },
    {
      "text": "El a primit cele mai multe voturi la alegeri."
    },
    {
      "text": "Votul contează în procesele democratice."
    }
  ],
  "relatedWords": [
    {
      "text": "votare"
    },
    {
      "text": "candidat"
    },
    {
      "text": "buletin de vot"
    },
    {
      "text": "alegere"
    }
  ]
}